{
  "1호선": {
    "color": "#0052A4",
    "stationCodes": [
      "0150",
      "0151",
      "0152",
      "0153",
      "0154",
      "0155",
      "0159",
      "0156",
      "0157",
      "0158"
    ]
  },
  "2호선": {
    "color": "#00A84D",
    "stationCodes": [
      "0202",
      "0203",
      "0204",
      "0205",
      "0206",
      "0207",
      "0208",
      "0209",
      "0210",
      "0211",
      "0212",
      "0213",
      "0214",
      "0215",
      "0216",
      "0217",
      "0218",
      "0219",
      "0220",
      "0221",
      "0222",
      "0223",
      "0224",
      "0225",
      "0226",
      "0227",
      "0228",
      "0229",
      "0230",
      "0231",
      "0232",
      "0233",
      "0234",
      "0235",
      "0236",
      "0237",
      "0238",
      "0239",
      "0240",
      "0241",
      "0242",
      "0243",
      "0201",
      "0246",
      "0250",
      "0245",
      "0244",
      "0247",
      "0248",
      "0249",
      "0200"
    ],
    "circular": true
  },
  "3호선": {
    "color": "#EF7C1C",
    "stationCodes": [
      "0309",
      "0310",
      "0311",
      "0312",
      "0313",
      "0314",
      "0315",
      "0316",
      "0317",
      "0318",
      "0319",
      "0320",
      "0321",
      "0322",
      "0323",
      "0324",
      "0325",
      "0326",
      "0327",
      "0328",
      "0329",
      "0330",
      "0331",
      "0332",
      "0333",
      "0334",
      "0335",
      "0336",
      "0337",
      "0338",
      "0339",
      "0340",
      "0341",
      "0342"
    ]
  },
  "4호선": {
    "color": "#00A5DE",
    "stationCodes": [
      "0409",
      "0410",
      "0411",
      "0412",
      "0413",
      "0414",
      "0415",
      "0416",
      "0417",
      "0418",
      "0419",
      "0420",
      "0421",
      "0422",
      "0423",
      "0424",
      "0425",
      "0426",
      "0427",
      "0428",
      "0429",
      "0430",
      "0431",
      "0432",
      "0433",
      "0434"
    ]
  },
  "5호선": {
    "color": "#996CAC",
    "stationCodes": [
      "2511",
      "2512",
      "2513",
      "2514",
      "2515",
      "2516",
      "2517",
      "2518",
      "2519",
      "2520",
      "2521",
      "2522",
      "2523",
      "2524",
      "2525",
      "2526",
      "2527",
      "2528",
      "2529",
      "2530",
      "2531",
      "2532",
      "2533",
      "2534",
      "2535",
      "2536",
      "2537",
      "2538",
      "2539",
      "2540",
      "2541",
      "2542",
      "2543",
      "2544",
      "2545",
      "2546",
      "2547",
      "2548",
      "2549",
      "2550",
      "2551",
      "2552",
      "2553",
      "2554",
      "2555",
      "2556",
      "2557",
      "2558",
      "2559",
      "2560",
      "2561",
      "2562",
      "2563",
      "2564",
      "2565",
      "2566"
    ]
  },
  "6호선": {
    "color": "#CD7C2F",
    "stationCodes": [
      "2611",
      "2612",
      "2613",
      "2614",
      "2616",
      "2617",
      "2618",
      "2619",
      "2620",
      "2621",
      "2622",
      "2623",
      "2624",
      "2625",
      "2626",
      "2627",
      "2628",
      "2629",
      "2630",
      "2631",
      "2632",
      "2633",
      "2634",
      "2635",
      "2636",
      "2637",
      "2638",
      "2639",
      "2640",
      "2641",
      "2642",
      "2643",
      "2644",
      "2645",
      "2646",
      "2647",
      "2648",
      "2615",
      "2649"
    ]
  },
  "7호선": {
    "color": "#747F00",
    "stationCodes": [
      "2711",
      "2712",
      "2713",
      "2714",
      "2715",
      "2716",
      "2717",
      "2718",
      "2719",
      "2720",
      "2721",
      "2722",
      "2723",
      "2724",
      "2725",
      "2726",
      "2727",
      "2728",
      "2729",
      "2730",
      "2731",
      "2732",
      "2733",
      "2734",
      "2735",
      "2736",
      "2737",
      "2738",
      "2739",
      "2740",
      "2741",
      "2742",
      "2743",
      "2744",
      "2745",
      "2746",
      "2747",
      "2748",
      "2749",
      "2750",
      "2751",
      "2752"
    ]
  },
  "8호선": {
    "color": "#E6186C",
    "stationCodes": [
      "2811",
      "2812",
      "2813",
      "2814",
      "2815",
      "2816",
      "2817",
      "2818",
      "2819",
      "2820",
      "2821",
      "2828",
      "2822",
      "2823",
      "2824",
      "2825",
      "2826",
      "2827"
    ]
  }
}